notifier/__init__.py
notifier/core.py
notifier/testy.py
notifier/emojis/basketball.gif
notifier/emojis/bolt.gif
notifier/emojis/cake.gif
notifier/emojis/clover.gif
notifier/emojis/cookie.gif
notifier/emojis/cupcake.gif
notifier/emojis/donut.gif
notifier/emojis/duck-sad.gif
notifier/emojis/explosion.gif
notifier/emojis/fire.gif
notifier/emojis/fish.gif
notifier/emojis/frog.gif
notifier/emojis/graph-up.gif
notifier/emojis/herb.gif
notifier/emojis/luggage.gif
notifier/emojis/magic.gif
notifier/emojis/moai.gif
notifier/emojis/rocket.gif
notifier/emojis/tree.gif
notifier/sound/intro.wav
notifier/sound/pitch.wav
notifier/sound/pop.wav
notifier_ctk-0.1.2.dist-info/licenses/LICENSE
notifier_ctk-0.1.2.dist-info/METADATA
notifier_ctk-0.1.2.dist-info/WHEEL
notifier_ctk-0.1.2.dist-info/top_level.txt
notifier_ctk-0.1.2.dist-info/RECORD
